clinv/__init__.py
clinv/adapters/__init__.py
clinv/adapters/abstract.py
clinv/adapters/aws.py
clinv/adapters/fake.py
clinv/adapters/risk.py
clinv/config.py
clinv/entrypoints/__init__.py
clinv/entrypoints/cli.py
clinv/entrypoints/tui.py
clinv/model/__init__.py
clinv/model/aws.py
clinv/model/entity.py
clinv/model/risk.py
clinv/py.typed
clinv/services.py
clinv/version.py
clinv/views.py
clinv-1.6.3.dist-info/entry_points.txt
clinv-1.6.3.dist-info/WHEEL
clinv-1.6.3.dist-info/METADATA
clinv-1.6.3.dist-info/licenses/LICENSE
clinv-1.6.3.dist-info/licenses/COPYING
clinv-1.6.3.dist-info/RECORD
