Metadata-Version: 2.1
Name: clinv
Version: 1.6.3
Summary: DevSecOps command line asset inventory
License: GPL-3.0-only
Author-email: Lyz <lyz-code-security-advisories@riseup.net>
Requires-Python: >=3.7.2
Classifier: Development Status :: 2 - Pre-Alpha
Classifier: Intended Audience :: Developers
Classifier: License :: OSI Approved :: GNU General Public License v3 (GPLv3)
Classifier: Natural Language :: English
Classifier: Operating System :: POSIX
Classifier: Operating System :: Unix
Classifier: Programming Language :: Python
Classifier: Programming Language :: Python :: 3
Classifier: Programming Language :: Python :: 3.10
Classifier: Programming Language :: Python :: 3.7
Classifier: Programming Language :: Python :: 3.8
Classifier: Programming Language :: Python :: 3.9
Classifier: Topic :: Utilities
Requires-Dist: boto3>=1.20.24
Requires-Dist: click>=8.1.3
Requires-Dist: goodconf[yaml]>=2.0.1
Requires-Dist: prompt-toolkit>=3.0.29
Requires-Dist: questionary>=1.10.0
Requires-Dist: repository-orm>=0.7.0
Requires-Dist: requests>=2.26.0
Requires-Dist: rich>=10.16.0
Project-URL: Issues, https://github.com/lyz-code/clinv/issues
Project-URL: documentation, https://lyz-code.github.io/clinv
Project-URL: homepage, https://github.com/lyz-code/clinv
